[
  {
      "momId": "20230625140531",
      "title": "Meeting 1",
      "venue": "HQ",
      "meetingDate": "23/06/2023 11:00",
      "chairPerson": "MD",
      "mode": "Virtual",
      "keywords": "IR, FB",
      "momAttendeesResponse": [],
      "momActionResponse": [],
      "editedBy": "kumar3.nirmal@cris.org.in",
      "editTime": "25/06/2023 14:05",
      "remarks": " ",
      "status": "CREATE",
      "linkedMOM": " ",
      "pdfFile": "",
      "momEditHistoryResponse": null
  },
  {
      "momId": "MOM-20230625142654",
      "title": "Meeting 2",
      "venue": "HQ",
      "meetingDate": "23/06/2023 11:00",
      "chairPerson": "MD",
      "mode": "Virtual",
      "keywords": "IR, FB",
      "momAttendeesResponse": [],
      "momActionResponse": [],
      "editedBy": "kumar3.nirmal@cris.org.in",
      "editTime": "25/06/2023 14:26",
      "remarks": " ",
      "status": "CREATE",
      "linkedMOM": " ",
      "pdfFile": "",
      "momEditHistoryResponse": null
  },
  {
      "momId": "MOM-20230625150649",
      "title": "Meeting 3",
      "venue": "HQ",
      "meetingDate": "23/06/2023 11:00",
      "chairPerson": "MD",
      "mode": "Virtual",
      "keywords": "IR, FB",
      "momAttendeesResponse": [],
      "momActionResponse": [],
      "editedBy": "kumar3.nirmal@cris.org.in",
      "editTime": "25/06/2023 15:06",
      "remarks": " ",
      "status": "CREATE",
      "linkedMOM": " ",
      "pdfFile": "",
      "momEditHistoryResponse": null
  },
  {
      "momId": "MOM-20230625150836",
      "title": "Meeting 4",
      "venue": "HQ",
      "meetingDate": "23/06/2023 11:00",
      "chairPerson": "MD",
      "mode": "Virtual",
      "keywords": "IR, FB",
      "momAttendeesResponse": [
          {
              "attendeesId": "ATN-202306251508361",
              "name": "Nirmal Kumar",
              "designation": "SPE",
              "organization": "CRIS",
              "email": "kumar3.nirmal@cris.org.in"
          }
      ],
      "momActionResponse": [
          {
              "momId": null,
              "actionId": "ACT-20230625152515",
              "decissionPoint": "Decision 1",
              "actionPoint": "Action 1",
              "status": "1"
          },
          {
              "momId": null,
              "actionId": "ACT-202306251527102",
              "decissionPoint": "Decision 1",
              "actionPoint": "Action 1",
              "status": "1"
          }
      ],
      "editedBy": "kumar3.nirmal@cris.org.in",
      "editTime": "25/06/2023 15:08",
      "remarks": " ",
      "status": "CREATE",
      "linkedMOM": " ",
      "pdfFile": "",
      "momEditHistoryResponse": null
  },
  {
      "momId": "MOM-20230625153506",
      "title": "Meeting 5",
      "venue": "HQ",
      "meetingDate": "23/06/2023 11:00",
      "chairPerson": "MD",
      "mode": "Virtual",
      "keywords": "IR, FB",
      "momAttendeesResponse": [
          {
              "attendeesId": "ATN-202306251535061",
              "name": "Nirmal Kumar",
              "designation": "SPE",
              "organization": "CRIS",
              "email": "kumar3.nirmal@cris.org.in"
          }
      ],
      "momActionResponse": [
          {
              "momId": null,
              "actionId": "ACT-202306251535251",
              "decissionPoint": "Decision 1",
              "actionPoint": "Action 1",
              "status": "1"
          },
          {
              "momId": null,
              "actionId": "ACT-202306251840591",
              "decissionPoint": "Decision 3",
              "actionPoint": "Action 3",
              "status": "1"
          },
          {
              "momId": null,
              "actionId": "ACT-202306252017251",
              "decissionPoint": "Decision 2",
              "actionPoint": "Action 2",
              "status": "OPEN"
          }
      ],
      "editedBy": "kumar3.nirmal@cris.org.in",
      "editTime": "25/06/2023 15:35",
      "remarks": " ",
      "status": "CREATE",
      "linkedMOM": "MOM-20230625142654",
      "pdfFile": "",
      "momEditHistoryResponse": null
  },
  {
      "momId": "MOM-20230626102919",
      "title": "Meeting 6",
      "venue": "HQ",
      "meetingDate": "25/06/2023 11:00",
      "chairPerson": "MD",
      "mode": "Virtual",
      "keywords": "IR, FB",
      "momAttendeesResponse": [
          {
              "attendeesId": "ATN-202306261029191",
              "name": "Nirmal Kumar",
              "designation": "SPE",
              "organization": "CRIS",
              "email": "kumar3.nirmal@cris.org.in"
          }
      ],
      "momActionResponse": [
          {
              "momId": null,
              "actionId": "ACT-202306261029191",
              "decissionPoint": "Decision 1",
              "actionPoint": "Action 1",
              "status": "OPEN"
          },
          {
              "momId": null,
              "actionId": "ACT-202306261029192",
              "decissionPoint": "Decision 2",
              "actionPoint": "Action 2",
              "status": "OPEN"
          }
      ],
      "editedBy": "kumar3.nirmal@cris.org.in",
      "editTime": "26/06/2023 10:29",
      "remarks": " ",
      "status": "CREATE",
      "linkedMOM": "MOM-20230625142654",
      "pdfFile": "",
      "momEditHistoryResponse": null
  },
  {
      "momId": "MOM-20230626104203",
      "title": "Internal Meeting",
      "venue": "Office",
      "meetingDate": "26/06/2023 11:00",
      "chairPerson": "Priya Srivastav",
      "mode": "In-Person",
      "keywords": "Passenger Business & TCOE",
      "momAttendeesResponse": [
          {
              "attendeesId": "ATN-202306261432241",
              "name": "Priya Srivastav",
              "designation": "PPE",
              "organization": "CRIS",
              "email": "priya@cris.org.in"
          },
          {
              "attendeesId": "ATN-202306261432242",
              "name": "Rachna Singh rathore",
              "designation": "PPE",
              "organization": "CRIS",
              "email": "rachna@cris.org.in"
          }
      ],
      "momActionResponse": [
          {
              "momId": null,
              "actionId": "ACT-202306261432241",
              "decissionPoint": "Review Passenger Business",
              "actionPoint": "To be done by Bharti",
              "status": "OPEN"
          },
          {
              "momId": null,
              "actionId": "ACT-202306261432242",
              "decissionPoint": "Review of TCOE",
              "actionPoint": "To be done by Rachna",
              "status": "OPEN"
          }
      ],
      "editedBy": "priya@cris.org.in",
      "editTime": "26/06/2023 14:51",
      "remarks": "Make it final 3",
      "status": "APPROVED",
      "linkedMOM": "MOM-20230626102919",
      "pdfFile": "",
      "momEditHistoryResponse": null
  }
]